[
  {
    "name": "node",
    "type": "modify",
    "timestamp": "2015-12-12T18:56:23Z",
    "lon": 27.9282801,
    "lat": -28.9136352,
    "version": 2,
    "id": 2983759610,
    "user": "DeBigC"
  },
  {
    "name": "node",
    "type": "modify",
    "timestamp": "2015-12-12T18:56:23Z",
    "lon": 27.9278885,
    "lat": -28.9132995,
    "version": 3,
    "id": 2983772885,
    "user": "DeBigC"
  },
  {
    "name": "node",
    "type": "modify",
    "timestamp": "2015-12-12T18:56:23Z",
    "lon": 27.9280548,
    "lat": -28.9134521,
    "version": 2,
    "id": 2983778067,
    "user": "DeBigC"
  },
  {
    "name": "node",
    "type": "modify",
    "timestamp": "2015-12-12T18:56:23Z",
    "lon": 27.9284169,
    "lat": -28.9137432,
    "version": 2,
    "id": 2983778068,
    "user": "DeBigC"
  },
  {
    "name": "node",
    "type": "modify",
    "timestamp": "2015-12-12T18:56:23Z",
    "lon": 27.9284371,
    "lat": -28.9166486,
    "version": 2,
    "id": 3654813419,
    "user": "DeBigC"
  },
  {
    "name": "node",
    "type": "modify",
    "timestamp": "2015-12-12T18:56:23Z",
    "lon": 27.9283772,
    "lat": -28.9167155,
    "version": 2,
    "id": 3654813420,
    "user": "DeBigC"
  },
  {
    "name": "node",
    "type": "modify",
    "timestamp": "2015-12-12T18:56:23Z",
    "lon": 27.928481,
    "lat": -28.9167996,
    "version": 2,
    "id": 3654813421,
    "user": "DeBigC"
  },
  {
    "name": "node",
    "type": "modify",
    "timestamp": "2015-12-12T18:56:23Z",
    "lon": 27.9285666,
    "lat": -28.916704,
    "version": 2,
    "id": 3654813422,
    "user": "DeBigC"
  },
  {
    "name": "node",
    "type": "modify",
    "timestamp": "2015-12-12T18:56:23Z",
    "lon": 27.9284888,
    "lat": -28.9166507,
    "version": 2,
    "id": 3654813423,
    "user": "DeBigC"
  },
  {
    "name": "node",
    "type": "modify",
    "timestamp": "2015-12-12T18:56:23Z",
    "lon": 27.9284702,
    "lat": -28.9166714,
    "version": 2,
    "id": 3654813424,
    "user": "DeBigC"
  },
  {
    "name": "node",
    "type": "modify",
    "timestamp": "2015-12-12T18:56:23Z",
    "lon": 27.9280429,
    "lat": -28.915889,
    "version": 2,
    "id": 3654841673,
    "user": "DeBigC"
  },
  {
    "name": "node",
    "type": "modify",
    "timestamp": "2015-12-12T18:56:23Z",
    "lon": 27.9280824,
    "lat": -28.9158516,
    "version": 2,
    "id": 3654841674,
    "user": "DeBigC"
  },
  {
    "name": "node",
    "type": "modify",
    "timestamp": "2015-12-12T18:56:23Z",
    "lon": 27.928108,
    "lat": -28.9158723,
    "version": 2,
    "id": 3654841675,
    "user": "DeBigC"
  },
  {
    "name": "node",
    "type": "modify",
    "timestamp": "2015-12-12T18:56:23Z",
    "lon": 27.9281427,
    "lat": -28.9158395,
    "version": 2,
    "id": 3654841676,
    "user": "DeBigC"
  },
  {
    "name": "node",
    "type": "modify",
    "timestamp": "2015-12-12T18:56:23Z",
    "lon": 27.9282189,
    "lat": -28.915901,
    "version": 2,
    "id": 3654841677,
    "user": "DeBigC"
  },
  {
    "name": "node",
    "type": "delete",
    "timestamp": "2015-12-12T18:56:24Z",
    "lon": 27.9281759,
    "lat": -28.9159417,
    "version": 2,
    "id": 3654841678,
    "user": "DeBigC"
  },
  {
    "name": "node",
    "type": "modify",
    "timestamp": "2015-12-12T18:56:23Z",
    "lon": 27.928128,
    "lat": -28.9159873,
    "version": 2,
    "id": 3654841679,
    "user": "DeBigC"
  },
  {
    "name": "node",
    "type": "modify",
    "timestamp": "2015-12-12T18:56:23Z",
    "lon": 27.9280694,
    "lat": -28.91594,
    "version": 2,
    "id": 3654841680,
    "user": "DeBigC"
  },
  {
    "name": "node",
    "type": "modify",
    "timestamp": "2015-12-12T18:56:23Z",
    "lon": 27.9280795,
    "lat": -28.9159304,
    "version": 2,
    "id": 3654841681,
    "user": "DeBigC"
  },
  {
    "name": "node",
    "type": "modify",
    "timestamp": "2015-12-12T18:56:23Z",
    "lon": 27.9280615,
    "lat": -28.9136381,
    "version": 2,
    "id": 3654944657,
    "user": "DeBigC"
  },
  {
    "name": "node",
    "type": "modify",
    "timestamp": "2015-12-12T18:56:23Z",
    "lon": 27.928016,
    "lat": -28.9136881,
    "version": 2,
    "id": 3654944658,
    "user": "DeBigC"
  },
  {
    "name": "node",
    "type": "modify",
    "timestamp": "2015-12-12T18:56:23Z",
    "lon": 27.928087,
    "lat": -28.9137488,
    "version": 2,
    "id": 3654944659,
    "user": "DeBigC"
  },
  {
    "name": "node",
    "type": "modify",
    "timestamp": "2015-12-12T18:56:23Z",
    "lon": 27.9281377,
    "lat": -28.9137033,
    "version": 2,
    "id": 3654944660,
    "user": "DeBigC"
  },
  {
    "name": "node",
    "type": "create",
    "timestamp": "2015-12-12T18:56:22Z",
    "lon": 27.9280337,
    "lat": -28.9136631,
    "version": 1,
    "id": 3889457629,
    "user": "DeBigC"
  },
  {
    "name": "node",
    "type": "create",
    "timestamp": "2015-12-12T18:56:22Z",
    "lon": 27.9280367,
    "lat": -28.9136696,
    "version": 1,
    "id": 3889457630,
    "user": "DeBigC"
  },
  {
    "name": "node",
    "type": "create",
    "timestamp": "2015-12-12T18:56:22Z",
    "lon": 27.9291277,
    "lat": -28.9148715,
    "version": 1,
    "id": 3889457631,
    "user": "DeBigC"
  },
  {
    "name": "node",
    "type": "create",
    "timestamp": "2015-12-12T18:56:22Z",
    "lon": 27.9291135,
    "lat": -28.9148855,
    "version": 1,
    "id": 3889457632,
    "user": "DeBigC"
  },
  {
    "name": "node",
    "type": "create",
    "timestamp": "2015-12-12T18:56:22Z",
    "lon": 27.929129,
    "lat": -28.9148976,
    "version": 1,
    "id": 3889457633,
    "user": "DeBigC"
  },
  {
    "name": "node",
    "type": "create",
    "timestamp": "2015-12-12T18:56:22Z",
    "lon": 27.9291433,
    "lat": -28.9148837,
    "version": 1,
    "id": 3889457634,
    "user": "DeBigC"
  },
  {
    "name": "node",
    "type": "create",
    "timestamp": "2015-12-12T18:56:22Z",
    "lon": 27.9280595,
    "lat": -28.9159142,
    "version": 1,
    "id": 3889457635,
    "user": "DeBigC"
  },
  {
    "name": "node",
    "type": "create",
    "timestamp": "2015-12-12T18:56:22Z",
    "lon": 27.9280662,
    "lat": -28.9159079,
    "version": 1,
    "id": 3889457636,
    "user": "DeBigC"
  },
  {
    "name": "node",
    "type": "create",
    "timestamp": "2015-12-12T18:56:22Z",
    "lon": 27.9284437,
    "lat": -28.9167611,
    "version": 1,
    "id": 3889457637,
    "user": "DeBigC"
  },
  {
    "name": "node",
    "type": "create",
    "timestamp": "2015-12-12T18:56:22Z",
    "lon": 27.9284365,
    "lat": -28.9167691,
    "version": 1,
    "id": 3889457638,
    "user": "DeBigC"
  },
  {
    "name": "node",
    "type": "create",
    "timestamp": "2015-12-12T18:56:22Z",
    "lon": 27.9311785,
    "lat": -28.9121904,
    "version": 1,
    "id": 3889457639,
    "user": "DeBigC"
  },
  {
    "name": "node",
    "type": "create",
    "timestamp": "2015-12-12T18:56:23Z",
    "lon": 27.9311848,
    "lat": -28.9122139,
    "version": 1,
    "id": 3889457640,
    "user": "DeBigC"
  },
  {
    "name": "node",
    "type": "create",
    "timestamp": "2015-12-12T18:56:23Z",
    "lon": 27.9312253,
    "lat": -28.9122056,
    "version": 1,
    "id": 3889457641,
    "user": "DeBigC"
  },
  {
    "name": "node",
    "type": "create",
    "timestamp": "2015-12-12T18:56:23Z",
    "lon": 27.931219,
    "lat": -28.9121821,
    "version": 1,
    "id": 3889457642,
    "user": "DeBigC"
  }
]
